hf_olmo/__init__.py
hf_olmo/configuration_olmo.py
hf_olmo/convert_olmo_to_hf.py
hf_olmo/modeling_olmo.py
hf_olmo/tokenization_olmo_fast.py
olmo/__init__.py
olmo/aliases.py
olmo/beam_search.py
olmo/checkpoint.py
olmo/config.py
olmo/exceptions.py
olmo/initialization.py
olmo/model.py
olmo/optim.py
olmo/py.typed
olmo/safetensors_util.py
olmo/tokenizer.py
olmo/torch_util.py
olmo/train.py
olmo/util.py
olmo/version.py
olmo/data/__init__.py
olmo/data/collator.py
olmo/data/iterable_dataset.py
olmo/data/memmap_dataset.py
olmo/data/named_data_mixes.py
olmo/data/util.py
olmo/eval/__init__.py
olmo/eval/downstream.py
olmo/eval/evaluator.py
olmo_data/__init__.py
olmo_data/data.py
olmo_data/hf_datasets/ai2_arc/ARC-Challenge/validation/data-00000-of-00001.arrow
olmo_data/hf_datasets/ai2_arc/ARC-Challenge/validation/dataset_info.json
olmo_data/hf_datasets/ai2_arc/ARC-Challenge/validation/state.json
olmo_data/hf_datasets/ai2_arc/ARC-Easy/validation/data-00000-of-00001.arrow
olmo_data/hf_datasets/ai2_arc/ARC-Easy/validation/dataset_info.json
olmo_data/hf_datasets/ai2_arc/ARC-Easy/validation/state.json
olmo_data/hf_datasets/allenai/basic_arithmetic/none/validation/data-00000-of-00001.arrow
olmo_data/hf_datasets/allenai/basic_arithmetic/none/validation/dataset_info.json
olmo_data/hf_datasets/allenai/basic_arithmetic/none/validation/state.json
olmo_data/hf_datasets/boolq/none/validation/data-00000-of-00001.arrow
olmo_data/hf_datasets/boolq/none/validation/dataset_info.json
olmo_data/hf_datasets/boolq/none/validation/state.json
olmo_data/hf_datasets/glue/mrpc/validation/data-00000-of-00001.arrow
olmo_data/hf_datasets/glue/mrpc/validation/dataset_info.json
olmo_data/hf_datasets/glue/mrpc/validation/state.json
olmo_data/hf_datasets/glue/rte/validation/data-00000-of-00001.arrow
olmo_data/hf_datasets/glue/rte/validation/dataset_info.json
olmo_data/hf_datasets/glue/rte/validation/state.json
olmo_data/hf_datasets/glue/sst2/validation/data-00000-of-00001.arrow
ai2_olmo-0.6.0.dist-info/LICENSE
ai2_olmo-0.6.0.dist-info/METADATA
ai2_olmo-0.6.0.dist-info/WHEEL
ai2_olmo-0.6.0.dist-info/top_level.txt
ai2_olmo-0.6.0.dist-info/RECORD
