Metadata-Version: 2.1
Name: ai2-olmo
Version: 0.6.0
Summary: Open Language Model (OLMo)
Author-email: Allen Institute for Artificial Intelligence <olmo@allenai.org>
License:                                  Apache License
Project-URL: Homepage, https://github.com/allenai/OLMo
Project-URL: Repository, https://github.com/allenai/OLMo
Requires-Python: >=3.8
License-File: LICENSE
Requires-Dist: numpy<2
Requires-Dist: torch>=2.1
Requires-Dist: ai2-olmo-core==0.1.0
Requires-Dist: omegaconf
Requires-Dist: rich
Requires-Dist: boto3
Requires-Dist: google-cloud-storage
Requires-Dist: tokenizers
Requires-Dist: packaging
Requires-Dist: cached_path>=1.6.2
Requires-Dist: transformers
Requires-Dist: importlib_resources
Provides-Extra: dev
Requires-Dist: ruff; extra == "dev"
Requires-Dist: mypy<1.4,>=1.0; extra == "dev"
Requires-Dist: black<24.0,>=23.1; extra == "dev"
Requires-Dist: isort<5.13,>=5.12; extra == "dev"
Requires-Dist: pytest; extra == "dev"
Requires-Dist: pytest-sphinx; extra == "dev"
Requires-Dist: twine>=1.11.0; extra == "dev"
Requires-Dist: setuptools; extra == "dev"
Requires-Dist: wheel; extra == "dev"
Requires-Dist: build; extra == "dev"
Provides-Extra: train
Requires-Dist: wandb; extra == "train"
Requires-Dist: beaker-gantry; extra == "train"
Requires-Dist: click; extra == "train"
Requires-Dist: torchmetrics; extra == "train"
Requires-Dist: smashed[remote]>=0.21.1; extra == "train"
Requires-Dist: safetensors; extra == "train"
Requires-Dist: datasets; extra == "train"
Requires-Dist: scikit-learn; extra == "train"
Requires-Dist: msgspec>=0.14.0; extra == "train"
Provides-Extra: all
Requires-Dist: ai2-olmo[dev,train]; extra == "all"
